solana_charts/__init__.py
solana_charts/prices.py
solana_charts-0.0.2.dist-info/METADATA
solana_charts-0.0.2.dist-info/WHEEL
solana_charts-0.0.2.dist-info/top_level.txt
solana_charts-0.0.2.dist-info/RECORD
