Metadata-Version: 2.4
Name: solana-charts
Version: 0.0.2
Summary: Solana charts package
Classifier: Programming Language :: Python :: 3
Classifier: Operating System :: OS Independent
Requires-Python: >=3.9
